figma_mcp_server/__init__.py
figma_mcp_server/cli.py
figma_mcp_server/figma_parser.py
figma_mcp_server/figma_service.py
figma_mcp_server/figma_transformers.py
figma_mcp_server/figma_utils.py
figma_mcp_server/main.py
figma_mcp_server/models.py
figma_mcp_server-0.1.2.dist-info/METADATA
figma_mcp_server-0.1.2.dist-info/WHEEL
figma_mcp_server-0.1.2.dist-info/entry_points.txt
figma_mcp_server-0.1.2.dist-info/top_level.txt
figma_mcp_server-0.1.2.dist-info/RECORD
