Metadata-Version: 2.4
Name: figma-mcp-server
Version: 0.1.2
Summary: A Model Context Protocol (MCP) server for Figma data extraction with component and design token focus
Author-email: Kang Byungmin <byungmin.kang@snowcorp.com>
Maintainer-email: Kang Byungmin <byungmin.kang@snowcorp.com>
Project-URL: Homepage, https://github.com/user/figma-mcp
Project-URL: Repository, https://github.com/user/figma-mcp.git
Project-URL: Issues, https://github.com/user/figma-mcp/issues
Project-URL: Documentation, https://github.com/user/figma-mcp#readme
Keywords: figma,mcp,design-tokens,components,ai,llm
Classifier: Development Status :: 4 - Beta
Classifier: Intended Audience :: Developers
Classifier: Operating System :: OS Independent
Classifier: Programming Language :: Python :: 3
Classifier: Programming Language :: Python :: 3.9
Classifier: Programming Language :: Python :: 3.10
Classifier: Programming Language :: Python :: 3.11
Classifier: Programming Language :: Python :: 3.12
Classifier: Topic :: Software Development :: Libraries :: Python Modules
Classifier: Topic :: Internet :: WWW/HTTP :: HTTP Servers
Classifier: Topic :: Multimedia :: Graphics
Requires-Python: >=3.9
Requires-Dist: fastmcp>=2.0.0
Requires-Dist: httpx>=0.24.0
Requires-Dist: pydantic>=2.0.0
Requires-Dist: python-dotenv>=1.0.0
Requires-Dist: pyyaml>=6.0.0
Requires-Dist: aiofiles>=23.0.0
Provides-Extra: dev
Requires-Dist: pytest>=7.0.0; extra == "dev"
Requires-Dist: pytest-asyncio>=0.21.0; extra == "dev"
Requires-Dist: black>=23.0.0; extra == "dev"
Requires-Dist: isort>=5.12.0; extra == "dev"
Requires-Dist: mypy>=1.0.0; extra == "dev"
Requires-Dist: flake8>=6.0.0; extra == "dev"
